birdie/__init__.py
birdie/__version__.py
birdie/config.py
birdie/input.py
birdie/output.py
birdie/server.py
birdie-0.1.32.dist-info/licenses/LICENSE
birdie-0.1.32.dist-info/METADATA
birdie-0.1.32.dist-info/WHEEL
birdie-0.1.32.dist-info/top_level.txt
birdie-0.1.32.dist-info/RECORD
