Metadata-Version: 2.4
Name: birdie
Version: 0.1.32
Summary: A simple permissive framework to interact with the birdie platform
Requires-Python: >=3.13
License-File: LICENSE
Requires-Dist: fastapi>=0.119.0
Requires-Dist: httpx>=0.28.1
Requires-Dist: pydantic>=2.12.2
Requires-Dist: pytest>=9.0.1
Requires-Dist: pytest-asyncio>=1.3.0
Requires-Dist: toml>=0.10.2
Dynamic: license-file
